{"jeopardy":[{"category":"U.S.A.","clues":[{"value":200,"category":"U.S.A.","clue":"A 1991 railroad accident dumped 19,500 gallons of pesticide into this state's Sacramento River","answer":"California","daily_double?":false},{"value":400,"category":"U.S.A.","clue":"This phrase begins Kentucky's motto, which ends, \"divided we fall\"","answer":"United we stand","daily_double?":false},{"value":600,"category":"U.S.A.","clue":"This state capital is named for William Trent, a Colonial Chief Justice of New Jersey","answer":"Trenton","daily_double?":false},{"value":800,"category":"U.S.A.","clue":"In 1845 the town of Marthasville, Georgia was renamed this after the Western & Atlantic Railroad","answer":"Atlanta","daily_double?":false},{"value":1000,"category":"U.S.A.","clue":"This is Washington, D.C.'s oldest college as well as the oldest Catholic college in the nation","answer":"Georgetown","daily_double?":false}]},{"category":"SONG LYRICS","clues":[{"value":200,"category":"SONG LYRICS","clue":"Dolly Parton wrote, \"Working\" these hours, \"what a way to make a living\"","answer":"9 to 5","daily_double?":false},{"value":400,"category":"SONG LYRICS","clue":"\"Rock-a-bye your baby with\" one of these Southern tunes","answer":"a Dixie melody","daily_double?":false},{"value":600,"category":"SONG LYRICS","clue":"\"Love me or\" do this, \"and let me be lonely\"","answer":"leave me","daily_double?":false},{"value":800,"category":"SONG LYRICS","clue":"\"I'd love to get you on a slow boat to\" this place, \"all to myself, alone\"","answer":"China","daily_double?":false},{"value":1000,"category":"SONG LYRICS","clue":"\"The falling leaves drift by the window, the autumn leaves, of\" these 2 colors","answer":"red & gold","daily_double?":false}]},{"category":"WORLD ALMANAC 1868","clues":[{"value":200,"category":"WORLD ALMANAC 1868","clue":"The book lists 2 of these solar phenomena, including a total one","answer":"an eclipse","daily_double?":false},{"value":400,"category":"WORLD ALMANAC 1868","clue":"It's the chief wool-producing state, & we're not pulling the wool over your buckeyes","answer":"Ohio","daily_double?":false},{"value":600,"category":"WORLD ALMANAC 1868","clue":"On Nov. 14, 1867 there were meteor showers & this volcano near Naples erupted","answer":"Vesuvius","daily_double?":false},{"value":800,"category":"WORLD ALMANAC 1868","clue":"There are about 1,250,000 free & accepted ones of these around the world, including 100,000 in Scotland","answer":"Masons","daily_double?":false},{"value":1000,"category":"WORLD ALMANAC 1868","clue":"This U.S. president earns a big $25,000 a year","answer":"Andrew Johnson","daily_double?":true}]},{"category":"NOTABLE NAMES","clues":[{"value":200,"category":"NOTABLE NAMES","clue":"H.L. Mencken nicknamed him \"Roosevelt minor\"","answer":"Franklin Roosevelt","daily_double?":false},{"value":400,"category":"NOTABLE NAMES","clue":"1 of the 2 playwrights named Miller who won the Pulitzer Prize for Drama","answer":"Arthur Miller (or Jason Miller)","daily_double?":false},{"value":600,"category":"NOTABLE NAMES","clue":"He married Evita in 1945 & Isabel in 1961","answer":"Juan Perón","daily_double?":false},{"value":800,"category":"NOTABLE NAMES","clue":"This director produced many of his own films, including \"Strangers on a Train\"","answer":"Alfred Hitchcock","daily_double?":false},{"value":1000,"category":"NOTABLE NAMES","clue":"This prince consort was only 42 when he died of typhoid fever at Windsor Castle in 1861","answer":"Prince Albert","daily_double?":false}]},{"category":"QUOTES","clues":[{"value":200,"category":"QUOTES","clue":"This animal has been described as \"a pogo stick with a pouch\"","answer":"a kangaroo","daily_double?":false},{"value":400,"category":"QUOTES","clue":"Seneca wrote, \"What fools these mortals be\" centuries before this dramatist","answer":"Shakespeare","daily_double?":false},{"value":600,"category":"QUOTES","clue":"The quote \"I am looking for\" this type of \"man\" has been attributed to Aesop & to Diogenes the Cynic","answer":"an honest man","daily_double?":false},{"value":800,"category":"QUOTES","clue":"Aristotle said, \"One\" of these birds \"does not make a summer; neither does one fine day\"","answer":"a swallow","daily_double?":false},{"value":1000,"category":"QUOTES","clue":"The first line of \"The American Crisis, No. 1\", a 1776 tract by Thomas Paine","answer":"These are the times that try men's souls","daily_double?":false}]},{"category":"PIG ODDS & ENDS","clues":[{"value":200,"category":"PIG ODDS & ENDS","clue":"They're the parts of a baby's body referred to in rhyme as \"piggies\"","answer":"the toes","daily_double?":false},{"value":400,"category":"PIG ODDS & ENDS","clue":"It's the mixture of liquid & solid foods fed to pigs","answer":"slop (or swill)","daily_double?":false},{"value":600,"category":"PIG ODDS & ENDS","clue":"Collective term for pigs & hogs, or a brutish person","answer":"a swine","daily_double?":false},{"value":800,"category":"PIG ODDS & ENDS","clue":"3-letter synonym for piggery, a place where pigs are kept","answer":"a sty","daily_double?":false},{"value":1000,"category":"PIG ODDS & ENDS","clue":"Pig parts featured in the commodities market","answer":"pork bellies","daily_double?":false}]}],"comments":"","contestants":["Dennis Hartin","Camille Calman","Mike Boyd"],"categories":{"jeopardy":["U.S.A.","SONG LYRICS","WORLD ALMANAC 1868","NOTABLE NAMES","QUOTES","PIG ODDS & ENDS"],"double_jeopardy":["AFRICAN HISTORY","SCULPTURE","RANKS & TITLES","GENERAL SCIENCE","GOVERNMENT & POLITICS","CROSSWORD CLUES \"M\""],"final_jeopardy":"BUSINESS & INDUSTRY"},"season":"9","air_date":"1993-07-01","double_jeopardy":[{"category":"AFRICAN HISTORY","clues":[{"value":400,"category":"AFRICAN HISTORY","clue":"Zenodotus of Ephesus was this ancient library's first librarian","answer":"Alexandria","daily_double?":false},{"value":800,"category":"AFRICAN HISTORY","clue":"This country's 1954-1962 struggle for independence caused a million Europeans to leave it","answer":"Algeria","daily_double?":false},{"value":1200,"category":"AFRICAN HISTORY","clue":"Stanley found Livingstone in this country that merged with Zanzibar in 1964","answer":"Tanganyika","daily_double?":false},{"value":1600,"category":"AFRICAN HISTORY","clue":"450 years of Portuguese rule ended for this SE African nation when it became independent June 25, 1975","answer":"Mozambique","daily_double?":false},{"value":2000,"category":"AFRICAN HISTORY","clue":"Burton & Speke explored the Nile & Mungo Park explored this West African river","answer":"the Niger","daily_double?":false}]},{"category":"SCULPTURE","clues":[{"value":400,"category":"SCULPTURE","clue":"Michelangelo's works for Pope Julius II's tomb included an 8'4\" statue of this Biblical lawgiver","answer":"Moses","daily_double?":false},{"value":800,"category":"SCULPTURE","clue":"Gutzon Borglum's seated figure of this 16th president can be seen outside a Newark courthouse","answer":"Lincoln","daily_double?":false},{"value":1200,"category":"SCULPTURE","clue":"\"Cowboy on a Wild Pony\" by Constance Warren Whitney stands in front of this Sooner State's capitol building","answer":"Oklahoma","daily_double?":false},{"value":1600,"category":"SCULPTURE","clue":"Verrocchio's only surviving work in precious metal is a silver relief of \"The Beheading of\" this man","answer":"John the Baptist","daily_double?":false},{"value":2000,"category":"SCULPTURE","clue":"In 1884 Rodin began work on a monument honoring the self-sacrificing \"Burghers of\" this French city","answer":"Calais","daily_double?":true}]},{"category":"RANKS & TITLES","clues":[{"value":400,"category":"RANKS & TITLES","clue":"A vicereine is the wife of one of these","answer":"a viceroy","daily_double?":false},{"value":800,"category":"RANKS & TITLES","clue":"You're on a roll if you know this was the title of the German emperor from 1871 to 1918","answer":"Kaiser","daily_double?":false},{"value":1200,"category":"RANKS & TITLES","clue":"Thank heaven, or at least Maurice, for this lowest rank of the French nobility","answer":"chevalier","daily_double?":false},{"value":1600,"category":"RANKS & TITLES","clue":"Enter & sign in please with this admitting officer of a university","answer":"the registrar","daily_double?":false},{"value":2000,"category":"RANKS & TITLES","clue":"After retirement, this adjective can be added to one's title to make it honorary","answer":"emeritus","daily_double?":false}]},{"category":"GENERAL SCIENCE","clues":[{"value":400,"category":"GENERAL SCIENCE","clue":"Biologically speaking, something that is subcutaneous is beneath this","answer":"the skin","daily_double?":false},{"value":800,"category":"GENERAL SCIENCE","clue":"A mixture of 2 or more metals; alnico is a magnetic one","answer":"an alloy","daily_double?":false},{"value":1200,"category":"GENERAL SCIENCE","clue":"In the Northern Hemisphere, the summer one of these is on June 21 or 22, the longest day of the year","answer":"the solstice","daily_double?":false},{"value":1600,"category":"GENERAL SCIENCE","clue":"Matter has the \"potential\" form of this by virtue of its position or structure","answer":"energy","daily_double?":false},{"value":2000,"category":"GENERAL SCIENCE","clue":"Normally, the periods of this type of sleep are short early in the night, then lengthen","answer":"REM sleep","daily_double?":false}]},{"category":"GOVERNMENT & POLITICS","clues":[{"value":400,"category":"GOVERNMENT & POLITICS","clue":"This cabinet department administers minimum wage laws","answer":"the Labor Department","daily_double?":false},{"value":800,"category":"GOVERNMENT & POLITICS","clue":"Rep. William Miller was chosen as his running mate in 1964 partly because \"he drives Johnson nuts\"","answer":"Goldwater","daily_double?":false},{"value":1200,"category":"GOVERNMENT & POLITICS","clue":"Dale Bumpers was this state's governor from 1971 until 1975, when he entered the U.S. Senate","answer":"Arkansas","daily_double?":false},{"value":1600,"category":"GOVERNMENT & POLITICS","clue":"This Wisconsin Democrat chaired the House Armed Services Committee from 1985 to 1993","answer":"(Les) Aspin","daily_double?":true},{"value":2000,"category":"GOVERNMENT & POLITICS","clue":"This Michigan governor became Richard Nixon's first Secretary of H.U.D. in 1969","answer":"(George) Romney","daily_double?":false}]},{"category":"CROSSWORD CLUES \"M\"","clues":[{"value":400,"category":"CROSSWORD CLUES \"M\"","clue":"Finn or Mouse\n(6)","answer":"Mickey","daily_double?":false},{"value":800,"category":"CROSSWORD CLUES \"M\"","clue":"Kids shoot them, parents lose them\n(7)","answer":"marbles","daily_double?":false},{"value":1200,"category":"CROSSWORD CLUES \"M\"","clue":"Prime line\n(8)","answer":"meridian","daily_double?":false},{"value":1600,"category":"CROSSWORD CLUES \"M\"","clue":"Company lover\n(6)","answer":"misery","daily_double?":false},{"value":2000,"category":"CROSSWORD CLUES \"M\"","clue":"Sicily strait city\n(7)","answer":"Messina","daily_double?":false}]}],"final_jeopardy":{"category":"BUSINESS & INDUSTRY","clue":"The Brooklyn Flint Glass Works changed its name to this after moving to a N.Y. town of the same name","answer":"Corning"}}