{"comments":"2011 Kids Week game 3.","jeopardy":[{"category":"THINK FAST WITH U.S. PRESIDENTS","clues":[{"value":100,"category":"THINK FAST WITH U.S. PRESIDENTS","answer":"Obama","clue":"The one who married a Michelle"},{"value":200,"category":"THINK FAST WITH U.S. PRESIDENTS","answer":"Clinton","clue":"The one who had Al Gore as his Vice President"},{"value":300,"category":"THINK FAST WITH U.S. PRESIDENTS","answer":"FDR","clue":"The only President to be elected 4 times to the job"},{"value":400,"category":"THINK FAST WITH U.S. PRESIDENTS","answer":"","clue":""},{"value":500,"category":"THINK FAST WITH U.S. PRESIDENTS","answer":"","clue":""}]},{"category":"SUMMER GAMES","clues":[{"value":100,"category":"SUMMER GAMES","answer":"golf","clue":"Little Tigers know that the WMF is the World Federation for the \"Mini\" version of this sport--look out for the windmill"},{"value":200,"category":"SUMMER GAMES","answer":"horse","clue":"In this \"equine\" basketball game, you get a letter if you miss a shot & your rival makes one--if you spell the game, you lose"},{"value":300,"category":"SUMMER GAMES","answer":"marbles","clue":"Use soccer balls to play a giant version of this game where the shooter knocks rolling targets out of a ring"},{"value":400,"category":"SUMMER GAMES","answer":"hopscotch","clue":"Hinkspiel is a German version of this game where you jump from one numbered space to another"},{"value":500,"category":"SUMMER GAMES","answer":"a scavenger hunt","clue":"In one of these \"hunts\" named for the behavior of certain animals, you & your friends compete to gather items on a list"}]},{"category":"FOR KIDS","clues":[{"value":100,"category":"FOR KIDS","answer":"Heads Up, Seven Up","clue":"Recess?  Time for this game with a soft drink in its name, where a septet of students are \"it\""},{"value":200,"category":"FOR KIDS","answer":"Velcro","clue":"Get out the door faster in shoes that fasten using this material of tiny hooks & loops instead of laces"},{"value":300,"category":"FOR KIDS","answer":"Owly","clue":"In comic books, this kind-hearted bird is often seen with his friend, Wormie"},{"value":400,"category":"FOR KIDS","answer":"Lunchables","clue":"Ham & American sub is one of these Oscar Mayer combos that sound perfect for the noon meal"},{"value":500,"category":"FOR KIDS","answer":"Dan Zanes","clue":"DZ for short, this maker of music for the whole family used to be in a grown-up band, the Del Fuegos"}]},{"category":"ICE CREAM","clues":[{"value":100,"category":"ICE CREAM","answer":"Baskin-Robbins","clue":"More than 60 years ago, this brand started with 31 flavors; today it has over 1,000"},{"value":200,"category":"ICE CREAM","answer":"Dairy Queen","clue":"In January of 2011, pecans fruit & chocolaty bits in vanilla soft serve was this brand's \"Blizzard of the Month\""},{"value":300,"category":"ICE CREAM","answer":"Good Humor","clue":"Candy Center Crunch & Strawberry Shortcake are ice creams on a stick from this \"good\" company, man"},{"value":400,"category":"ICE CREAM","answer":"","clue":""},{"value":500,"category":"ICE CREAM","answer":"","clue":""}]},{"category":"WHAT WILL YOU BE WHEN YOU GROW UP?","clues":[{"value":100,"category":"WHAT WILL YOU BE WHEN YOU GROW UP?","answer":"an ostrich","clue":"After I hatch from my egg I'll keep growing and growing until I'm a mature seven foot tall one of these birds"},{"value":200,"category":"WHAT WILL YOU BE WHEN YOU GROW UP?","answer":"a frog","clue":"I look a little fishy right now at an early stage but soon I'll grow up & become this"},{"value":300,"category":"WHAT WILL YOU BE WHEN YOU GROW UP?","answer":"a ladybug","clue":"Don't recognize me?  I'm this beloved little beetle, still in the larval stage"},{"value":400,"category":"WHAT WILL YOU BE WHEN YOU GROW UP?","answer":"a sunflower","clue":"Eventually I'll bloom into one of these, with a  thousand  seeds or so"},{"value":500,"category":"WHAT WILL YOU BE WHEN YOU GROW UP?","answer":"an oak","clue":"An old proverb says that from the little item seen here here grow great ones of these trees"}]},{"category":"VOWELS","clues":[{"value":100,"category":"VOWELS","answer":"an A","clue":"With a plus, it's the highest grade possible on a standard report card"},{"value":200,"category":"VOWELS","answer":"e-mail","clue":"A book called \"Send\" is \"The Essential Guide\" to this type of \"mail\""},{"value":300,"category":"VOWELS","answer":"O","clue":"On the national anthem, it precedes \"Canada\""},{"value":400,"category":"VOWELS","answer":"I","clue":"In traditional usage, it's also a pronoun"},{"value":500,"category":"VOWELS","answer":"u","clue":"In non-traditional usage, like in text messages, it's also a pronoun"}]}],"air_date":"2011-07-06","double_jeopardy":[{"category":"MYTHOLOGY","clues":[{"value":200,"category":"MYTHOLOGY","answer":"Poseidon","clue":"This Greek god could command the waves of the sea & create storms"},{"value":400,"category":"MYTHOLOGY","answer":"Hera","clue":"This Greek goddess of marriage & childbirth was jealous of Zeus' frequent infidelities"},{"value":600,"category":"MYTHOLOGY","answer":"Thor","clue":"The Norse believed that during a thunderstorm, this god rode through the heavens on a chariot drawn by goats"},{"value":800,"category":"MYTHOLOGY","answer":"Aphrodite","clue":"Melanion had to ask for help from this Greek love goddess on how to win Atalanta's hand"},{"value":1000,"category":"MYTHOLOGY","answer":"Cerberus","clue":"This 3-headed watchdog eats mortals who dare enter the underworld"}]},{"category":"POP CULTURE","clues":[{"value":200,"category":"POP CULTURE","answer":"Jaden Smith","clue":"This son of Will Smith turns 13 this week & says math is his favorite subject-- let's get him a textbook"},{"value":400,"category":"POP CULTURE","answer":"Gnomeo","clue":"In a 2011 animated film, Emily Blunt voices Juliet & James McAvoy voices this other title character"},{"value":600,"category":"POP CULTURE","answer":"Zeke & Luther","clue":"On a Disney show, these 2 best friends try to be the world's greatest skateboarders"},{"value":800,"category":"POP CULTURE","answer":"America's Got Talent","clue":"Young singer Bianca Ryan won the first season of this TV show now judged by Sharon Osbourne & others"},{"value":1000,"category":"POP CULTURE","answer":"Herbert","clue":"A video game in the \"Club Penguin\" series is titled his \"Revenge\""}]},{"category":"IT'S A SCIENTIFIC FACT","clues":[{"value":200,"category":"IT'S A SCIENTIFIC FACT","answer":"Jupiter","clue":"Due to its size, this planet is responsible for the Kirkwood gaps in our galaxy's asteroid belt"},{"value":400,"category":"IT'S A SCIENTIFIC FACT","answer":"a pendulum","clue":"(Here is the clue. Pay attention to Sarah.) Chairs, a broom, some string, and a can full of sand are all you need for the experiment that creates one of these swinging devices, similar to the one physicist Foucault used to show the earth's rotation"},{"value":600,"category":"IT'S A SCIENTIFIC FACT","answer":"liquids","clue":"An emulsion is a mixture of 2 or more of these that don't dissolve in each other"},{"value":800,"category":"IT'S A SCIENTIFIC FACT","answer":"molecules","clue":"(Jimmy help us out, please.) Ice is not as heavy or dense as water. In fact, our little ice boat here floats because these smallest particles that consist of atoms expand and spread out."},{"value":1000,"category":"IT'S A SCIENTIFIC FACT","answer":"salt","clue":"Humans can drink sea water once it has been desalinated, meaning this has been removed"}]},{"category":"THE LIBRARY OF CONGRESS","clues":[{"value":200,"category":"THE LIBRARY OF CONGRESS","answer":"Old King Cole","clue":"The smallest book in the collection, 1/25 of an inch square, tells the story of this \"merry old soul\" in a nursery rhyme"},{"value":400,"category":"THE LIBRARY OF CONGRESS","answer":"laws that are passed by Congress","clue":"The loc.gov feature called Thomas lets you search for these made by Congress, like H.R. 575"},{"value":600,"category":"THE LIBRARY OF CONGRESS","answer":"Braille","clue":"In 1931 the library began providing sound recordings of books as well as books written in this"},{"value":800,"category":"THE LIBRARY OF CONGRESS","answer":"The Neverending Story","clue":"Kids' books are under PZ in the LOC's cataloging system; this Michael Ende \"Story\" is in the PZ7's"},{"value":1000,"category":"THE LIBRARY OF CONGRESS","answer":"the Psalms","clue":"The LOC holds the oldest book printed in North America, a 1640 translation of these Biblical verses"}]},{"category":"MAPS","clues":[{"value":200,"category":"MAPS","answer":"blue","clue":"Most maps typically use this color to depict bodies of water"},{"value":400,"category":"MAPS","answer":"the key (or legend)","clue":"This term refers to the box on a map that explains what the symbols and colors represent"},{"value":600,"category":"MAPS","answer":"McNally","clue":"In 1904 the company named for Rand & him produced its first road map"},{"value":800,"category":"MAPS","answer":"Edmund Halley","clue":"The world's first weather map was created by this English astronomer in 1686 & showed the trade winds"},{"value":1000,"category":"MAPS","answer":"a TomTom","clue":"TV commercials for this maker of car navigation devices feature such characters as DougDoug & SueSue"}]},{"category":"SPELL IT!","clues":[{"value":200,"category":"SPELL IT!","answer":"Q-U-A-K-E-R","clue":"Spell this Christian group that's often found before \"Oats\""},{"value":400,"category":"SPELL IT!","answer":"G-O-S-L-I-N-G","clue":"Spell this word for the young of a goose that's also the surname of an actor named Ryan"},{"value":600,"category":"SPELL IT!","answer":"M-I-L-L-I-M-E-T-E-R","clue":"Spell this metric measurement equal to .03937 of an inch"},{"value":800,"category":"SPELL IT!","answer":"","clue":""},{"value":1000,"category":"SPELL IT!","answer":"","clue":""}]}],"final_jeopardy":{"category":"U.S. STATE NAMES","answer":"Ohio","clue":"Of the 4 states that begin & end with the same vowel, the one that doesn't begin & end with the same letter as the other 3 states"},"categories":{"jeopardy":["THINK FAST WITH U.S. PRESIDENTS","SUMMER GAMES","FOR KIDS","ICE CREAM","WHAT WILL YOU BE WHEN YOU GROW UP?","VOWELS"],"double_jeopardy":["MYTHOLOGY","POP CULTURE","IT'S A SCIENTIFIC FACT","THE LIBRARY OF CONGRESS","MAPS","SPELL IT!"],"final_jeopardy":"U.S. STATE NAMES"},"contestants":["Andrew Zazzera","B.D. Schwarz","Emma Johnson"]}