{"air_date":"1996-12-31","contestants":["Mario Zaragoza","Cindy Giddle","Ted Senator"],"description":"","double_jeopardy":[{"answer_text":"Ulysses S. Grant","category":"SECRETARIES OF STATE","clue_text":"Elihu Washburne, who sponsored a bill making this man a Civil War general, became his secretary of state","round":"double_jeopardy","type":"standard","value":200},{"answer_text":"Punch","category":"NEWSPAPERS & MAGAZINES","clue_text":"William Makepeace Thackeray was an early staff member of this British humor magazine","round":"double_jeopardy","type":"standard","value":200},{"answer_text":"Pastels","category":"PAINTING & SCULPTURE","clue_text":"Delicately-hued portraits made with these pale crayonlike sticks were popular in the 1700s","round":"double_jeopardy","type":"standard","value":200},{"answer_text":"\"(The Adventures Of) Ozzie & Harriet\"","category":"1950S SITCOMS","clue_text":"The 1952 movie \"Here Come The Nelsons\" served as the pilot for this sitcom","round":"double_jeopardy","type":"standard","value":200},{"answer_text":"Rosary","category":"RELIGION","clue_text":"Used in the Roman Catholic Church, it's a circle of 50 beads attached to a crucifix","round":"double_jeopardy","type":"standard","value":200},{"answer_text":"Beatrix Potter","category":"WOMEN AUTHORS","clue_text":"The real first name of this Peter Rabbit creator was Helen","round":"double_jeopardy","type":"standard","value":200},{"answer_text":"Princeton","category":"SECRETARIES OF STATE","clue_text":"Tyler appointee Abel Upshur was expelled from the College of N.J., now called this, for being in a student rebellion","round":"double_jeopardy","type":"standard","value":400},{"answer_text":"Alberta","category":"NEWSPAPERS & MAGAZINES","clue_text":"This Canadian province's largest newspaper is the Edmonton Journal","round":"double_jeopardy","type":"standard","value":400},{"answer_text":"Mural","category":"PAINTING & SCULPTURE","clue_text":"A painting applied to & made integral with a wall or ceiling, its name is from Latin for \"wall\"","round":"double_jeopardy","type":"standard","value":400},{"answer_text":"Ralph Kramden","category":"1950S SITCOMS","clue_text":"This character was a bus driver for the Gotham Bus Company in New York City","round":"double_jeopardy","type":"standard","value":400},{"answer_text":"Shinto","category":"RELIGION","clue_text":"In the 18th century, this ancient Japanese religion was revived through the writings of Mabuchi & others","round":"double_jeopardy","type":"standard","value":400},{"answer_text":"The Cat","category":"WOMEN AUTHORS","clue_text":"In titles of mysteries by Lilian Jackson Braun, this animal precedes \"Who Saw Red\" & \"Who Played Brahms\"","round":"double_jeopardy","type":"standard","value":400},{"answer_text":"Warren Christopher","category":"SECRETARIES OF STATE","clue_text":"Strobe Talbott is his deputy","round":"double_jeopardy","type":"standard","value":600},{"answer_text":"Reader\\'s Digest","category":"NEWSPAPERS & MAGAZINES","clue_text":"In 1955 this monthly founded by DeWitt & Lila Wallace was forced to accept advertising for the first time","round":"double_jeopardy","type":"standard","value":600},{"answer_text":"Terra Cotta","category":"PAINTING & SCULPTURE","clue_text":"18th C. artist Clodion sculpted nymphs & satyrs from this fired clay whose name is Italian for \"baked earth\"","round":"double_jeopardy","type":"standard","value":600},{"answer_text":"\"Father Knows Best\"","category":"1950S SITCOMS","clue_text":"Robert Young also starred as Jim Anderson in an earlier radio version of this series","round":"double_jeopardy","type":"standard","value":600},{"answer_text":"Quakers","category":"RELIGION","clue_text":"In 1649 George Fox, leader of this movement, was jailed for interrupting a minister","round":"double_jeopardy","type":"standard","value":600},{"answer_text":"Edith Wharton","category":"WOMEN AUTHORS","clue_text":"This \"Age of Innocence\" author launched her career with a how-to book on \"The Decoration of Houses\"","round":"double_jeopardy","type":"standard","value":600},{"answer_text":"Daniel Webster","category":"SECRETARIES OF STATE","clue_text":"With Lord Ashburton he negotiated the 1842 treaty that set the border for Maine","round":"double_jeopardy","type":"standard","value":800},{"answer_text":"Bruce Catton","category":"NEWSPAPERS & MAGAZINES","clue_text":"In 1954 this Civil War historian was named editor of American Heritage magazine","round":"double_jeopardy","type":"standard","value":800},{"answer_text":"tempera","category":"PAINTING & SCULPTURE","clue_text":"If this paint that has one egg yolk binder is applied too thickly, it may crack","round":"double_jeopardy","type":"standard","value":800},{"answer_text":"<i>Topper</i>","category":"1950S SITCOMS","clue_text":"(VIDEO DAILY DOUBLE)\nSeries that included this intro in its opening:\n\"Anne Jeffreys as Marion Kirby, the ghostess with the mostess\"","round":"double_jeopardy","type":"daily_double","value":800},{"answer_text":"Islam","category":"RELIGION","clue_text":"With over 1 billion followers, it's the largest non-Christian religion","round":"double_jeopardy","type":"daily_double","value":800},{"answer_text":"Colleen McCullough","category":"WOMEN AUTHORS","clue_text":"This \"Thorn Birds\" author is an admitted Scrabbleholic; she likes to play daily","round":"double_jeopardy","type":"standard","value":800},{"answer_text":"James G. Blaine","category":"SECRETARIES OF STATE","clue_text":"This man from Maine served James A. Garfield, Chester A. Arthur & Benjamin Harrison","round":"double_jeopardy","type":"standard","value":1000},{"answer_text":"George Plimpton","category":"NEWSPAPERS & MAGAZINES","clue_text":"Perhaps best known as a sportswriter, he's been editor-in-chief of the Paris Review since 1953","round":"double_jeopardy","type":"standard","value":1000},{"answer_text":"Kachinas","category":"PAINTING & SCULPTURE","clue_text":"Traditionally, Pueblo Indians carve these dolls that represent spirits as teaching devices for children","round":"double_jeopardy","type":"standard","value":1000},{"answer_text":"Richard Crenna","category":"1950S SITCOMS","clue_text":"In the 1950s this actor played Luke McCoy on \"The Real McCoys\" & Walter Denton on \"Our Miss Brooks\"","round":"double_jeopardy","type":"standard","value":1000},{"answer_text":"Vedas","category":"RELIGION","clue_text":"These oldest Hindu scriptures existed for centuries before they were written down","round":"double_jeopardy","type":"standard","value":1000},{"answer_text":"Virginia Woolf","category":"WOMEN AUTHORS","clue_text":"This British author dedicated her 1928 novel \"Orlando\" to Vita Sackville-West","round":"double_jeopardy","type":"standard","value":1000}],"double_jeopardy_round_categories":["SECRETARIES OF STATE","NEWSPAPERS & MAGAZINES","PAINTING & SCULPTURE","1950S SITCOMS","RELIGION","WOMEN AUTHORS"],"episode_num":2842,"final_jeopardy":{"answer_text":"Tom Hayden","category":"THE DEMOCRATIC NATIONAL CONVENTION","clue_text":"Arrested twice at the 1968 convention for demonstrating, he was a delegate to the 1996 convention","round":"final_jeopardy","type":"final_jeopardy"},"final_jeopardy_category":"THE DEMOCRATIC NATIONAL CONVENTION","id":6238,"jeopardy":[{"answer_text":"Declaration of Independence","category":"NOTABLE PHYSICIANS","clue_text":"Benjamin Rush was 1 of 4 practicing physicians who signed this 1776 document","round":"jeopardy","type":"standard","value":100},{"answer_text":"Hounds","category":"ODD WORDS","clue_text":"Yoicks was originally a cry meant to encourage these animals to pursue a fox","round":"jeopardy","type":"standard","value":100},{"answer_text":"Hairstyle","category":"FADS","clue_text":"Today Jennifer Aniston's is popular; in 1977 it was Farrah Fawcett's","round":"jeopardy","type":"standard","value":100},{"answer_text":"Eagle","category":"BIRDS","clue_text":"The shape of the letter A goes back to an Egyptian symbol for this bird, a symbol of the U.S.","round":"jeopardy","type":"standard","value":100},{"answer_text":"\"Sweet Georgia Brown\"","category":"SWEET SONGS","clue_text":"It's the theme song of the Harlem Globetrotters","round":"jeopardy","type":"standard","value":100},{"answer_text":"Utah","category":"COUNTIES BY STATE","clue_text":"Sanpete,\nSan Juan,\nSalt Lake","round":"jeopardy","type":"standard","value":100},{"answer_text":"Sigmund Freud","category":"NOTABLE PHYSICIANS","clue_text":"This father of psychoanalytic theory received his medical degree in Vienna in 1881","round":"jeopardy","type":"standard","value":200},{"answer_text":"Halo","category":"ODD WORDS","clue_text":"Gloriole is another name for this circle of light seen around the head of a saint","round":"jeopardy","type":"standard","value":200},{"answer_text":"Shirley Temple","category":"FADS","clue_text":"In the mid-'30s there were hats, shoes, glasses, books & dolls of this 6-year-old movie star","round":"jeopardy","type":"standard","value":200},{"answer_text":"Pelican","category":"BIRDS","clue_text":"It can weigh up to 33 pounds, its wingspan may reach 10 feet & it has a big pouch under its lower mandible","round":"jeopardy","type":"standard","value":200},{"answer_text":"Bing Crosby","category":"SWEET SONGS","clue_text":"This crooner's \"Sweet Leilani\" from the 1937 film \"Waikiki Wedding\" won an Oscar for best song","round":"jeopardy","type":"standard","value":200},{"answer_text":"Mississippi","category":"COUNTIES BY STATE","clue_text":"Jackson, \nJefferson,\nJefferson Davis","round":"jeopardy","type":"standard","value":200},{"answer_text":"Anemia","category":"NOTABLE PHYSICIANS","clue_text":"George Richards Minot discovered a way to treat the \"pernicious\" type of this through nutrition","round":"jeopardy","type":"standard","value":300},{"answer_text":"Drinks","category":"ODD WORDS","clue_text":"A compotator is a person who does this with another person -- how sociable","round":"jeopardy","type":"standard","value":300},{"answer_text":"Happy Face","category":"FADS","clue_text":"In 1971 wholesaler N.G. Slater sold 20 million buttons featuring this smiling expression","round":"jeopardy","type":"standard","value":300},{"answer_text":"Woodpecker","category":"BIRDS","clue_text":"Though it's a type of this bird, the flicker feeds on the ground, not by drilling holes in trees","round":"jeopardy","type":"standard","value":300},{"answer_text":"\"Sweet Gypsy Rose\"","category":"SWEET SONGS","clue_text":"In a Tony Orlando & Dawn song, \"She's got rings on her fingers and bells on her toes\"","round":"jeopardy","type":"standard","value":300},{"answer_text":"New York","category":"COUNTIES BY STATE","clue_text":"Chautauqua,\nCayuga,\nColumbia","round":"jeopardy","type":"standard","value":300},{"answer_text":"Heroin","category":"NOTABLE PHYSICIANS","clue_text":"Vincent Dole introduced the therapeutic use of methadone to control addiction to this","round":"jeopardy","type":"standard","value":400},{"answer_text":"Tongue","category":"ODD WORDS","clue_text":"A languet resembles this body part, in shape or in function","round":"jeopardy","type":"standard","value":400},{"answer_text":"Strawberry Shortcake","category":"FADS","clue_text":"This fruit-scented doll & her friends Lemon Meringue & Huckleberry Pie were big in the early '80s","round":"jeopardy","type":"standard","value":400},{"answer_text":"Hens","category":"BIRDS","clue_text":"On chicken farms females under a year old are called pullets; over a year old, they're called these","round":"jeopardy","type":"standard","value":400},{"answer_text":"The Eurythmics","category":"SWEET SONGS","clue_text":"\"Sweet Dreams (Are Made Of This)\" was the first No. 1 hit for this Annie Lennox duo","round":"jeopardy","type":"standard","value":400},{"answer_text":"Oklahoma","category":"COUNTIES BY STATE","clue_text":"Choctaw,\nCherokee,\nCimarron","round":"jeopardy","type":"standard","value":400},{"answer_text":"Albert Sabin","category":"NOTABLE PHYSICIANS","clue_text":"This oral polio vaccine pioneer was granted a medical degree 1 year after obtaining U.S. citizenship","round":"jeopardy","type":"standard","value":500},{"answer_text":"Yurt","category":"ODD WORDS","clue_text":"It's a portable circular domed tent used by Mongol nomads","round":"jeopardy","type":"standard","value":500},{"answer_text":"Stereopticons","category":"FADS","clue_text":"Long before the View-Master, these handheld 3-D stereoscopes were popular from 1850 to 1910","round":"jeopardy","type":"standard","value":500},{"answer_text":"Barn","category":"BIRDS","clue_text":"It's the man-made structure common to names of certain owls & swallows","round":"jeopardy","type":"standard","value":500},{"answer_text":"\"How Sweet It Is To Be Loved By You\"","category":"SWEET SONGS","clue_text":"Marvin Gaye & James Taylor each had a hit with this song","round":"jeopardy","type":"standard","value":500},{"answer_text":"Virginia","category":"COUNTIES BY STATE","clue_text":"Prince George,\nPrince William,\nPowhatan","round":"jeopardy","type":"daily_double","value":500}],"jeopardy_round_categories":["NOTABLE PHYSICIANS","ODD WORDS","FADS","BIRDS","SWEET SONGS","COUNTIES BY STATE"],"title":"Show #2842 - Tuesday, December 31, 1996"}