{"comments":"","jeopardy":[{"category":"COLORS","clues":[{"value":100,"category":"COLORS","clue":"3 colors in common to flags of the Netherlands, Thailand, Chile & U.S.","answer":"red, white & blue"},{"value":200,"category":"COLORS","clue":"Pachyderm seen by potted people","answer":"pink elephants"},{"value":300,"category":"COLORS","clue":"They're looked through to see the world in a wonderful light","answer":"rose-colored glasses"},{"value":400,"category":"COLORS","clue":"Pirate Edward Teach","answer":"Blackbeard"},{"value":500,"category":"COLORS","clue":"It can be filled with car prices or college test answers","answer":"a Blue Book"}]},{"category":"ROARING '20S","clues":[{"value":100,"category":"ROARING '20S","clue":"In '23 you could get 4 trillion, 200 billion marks for $1 in this country","answer":"Germany"},{"value":200,"category":"ROARING '20S","clue":"George Jessel & Eddie Cantor turned down the lead for this 1st talking movie","answer":"The Jazz Singer"},{"value":300,"category":"ROARING '20S","clue":"Appointed FBI Director in '24 at the age of 29","answer":"J. Edgar Hoover"},{"value":400,"category":"ROARING '20S","clue":"By police count, there were 32,000 of these illegal bars in NYC alone","answer":"speakeasies"},{"value":500,"category":"ROARING '20S","clue":"Played 1st of 2,130 consecutive baseball games, June 1, 1925","answer":"Lou Gehrig"}]},{"category":"TIME","clues":[{"value":100,"category":"TIME","clue":"Mike, Morley, Harry, Ed & sometimes Andy share this time","answer":"60 Minutes"},{"value":200,"category":"TIME","clue":"Dolly Parton kept these office hours","answer":"9 to 5"},{"value":300,"category":"TIME","clue":"Pro football's 15-minute show stopper","answer":"halftime"},{"value":400,"category":"TIME","clue":"The shortest in the solar system is Mercury's 88 days","answer":"orbital period (year)"},{"value":500,"category":"TIME","clue":"","answer":""}]},{"category":"LADIES IN SONG","clues":[{"value":100,"category":"LADIES IN SONG","clue":"Sounds like she's suing Michael Jackson for child support","answer":"\"Billie Jean\""},{"value":200,"category":"LADIES IN SONG","clue":"Salutation for Miss Parton of Nashville or Mrs. Levi of Yonkers","answer":"\"Hello, Dolly\""},{"value":300,"category":"LADIES IN SONG","clue":"She picked a fine time to leave","answer":"Lucille"},{"value":400,"category":"LADIES IN SONG","clue":"Stephen \"Fostered\" this dream about a lady with lovely tresses","answer":"\"Jeanie With The Light Brown Hair\""},{"value":500,"category":"LADIES IN SONG","clue":"Johnny Carson might ask \"Kool & the Gang\" not to sing this on \"The Tonight Show\":\n\n\"I'm in love, and I won't lie /\nShe's my girl and always on my mind /\nShe gives me her love and a feeling that's right...\"","answer":"\"Joanna\""}]},{"category":"FISH","clues":[{"value":100,"category":"FISH","clue":"Type of carp which might feel at home in Fort Knox","answer":"goldfish"},{"value":200,"category":"FISH","clue":"","answer":""},{"value":300,"category":"FISH","clue":"","answer":""},{"value":400,"category":"FISH","clue":"","answer":""},{"value":500,"category":"FISH","clue":"","answer":""}]},{"category":"SPORTS QUOTES","clues":[{"value":100,"category":"SPORTS QUOTES","clue":"Boxing champ noted for predicting: \"They must all fall, in the round I call\"","answer":"Muhammad Ali"},{"value":200,"category":"SPORTS QUOTES","clue":"\"Winning isn't everything, it's the only thing,\" said this Green Bay coach, so they say","answer":"Lombardi"},{"value":300,"category":"SPORTS QUOTES","clue":"What Leo Durocher replied when asked why he wasn't a nice guy","answer":"\"Nice guys finish last\""},{"value":400,"category":"SPORTS QUOTES","clue":"Celebrated Notre Dame football coach who asked team to \"win one for the Gipper\"","answer":"Knute Rockne"},{"value":500,"category":"SPORTS QUOTES","clue":"\"I want a man with enough guts not to fight back,\" Branch Rickey told him","answer":"Jackie Robinson"}]}],"air_date":"1984-10-26","categories":{"jeopardy":["COLORS","ROARING '20S","TIME","LADIES IN SONG","FISH","SPORTS QUOTES"],"double_jeopardy":["PRESIDENTS","TELEVISION","WORLD CAPITALS","BODY LANGUAGE","STARTS WITH \"P\"","CLASSICAL MUSIC"],"final_jeopardy":"U.S. STATES"},"contestants":["Peter Lalos","Diane Stone","Brad Marshall"],"double_jeopardy":[{"category":"PRESIDENTS","clues":[{"value":200,"category":"PRESIDENTS","clue":"Asked us \"Ask not what your country can do for you\"","answer":"John F. Kennedy"},{"value":400,"category":"PRESIDENTS","clue":"Like America, his 1st initials were U.S.","answer":"Grant"},{"value":600,"category":"PRESIDENTS","clue":"His 12-year term was the longest ever","answer":"Franklin Delano Roosevelt"},{"value":800,"category":"PRESIDENTS","clue":"He's considered both our 22nd & 24th president","answer":"Grover Cleveland"},{"value":1000,"category":"PRESIDENTS","clue":"Only impeached President, he kept his office by 1 vote","answer":"Andrew Johnson"}]},{"category":"TELEVISION","clues":[{"value":200,"category":"TELEVISION","clue":"Dynasty's dynamic downtown","answer":"Denver"},{"value":400,"category":"TELEVISION","clue":"He thought 3 was company but found out it was a crowd","answer":"John Ritter"},{"value":600,"category":"TELEVISION","clue":"Muppet monster or Dr. Gates on \"Trapper John\"","answer":"Gonzo"},{"value":800,"category":"TELEVISION","clue":"Initials shared by friends of Hawkeye & The Bear","answer":"B.J."},{"value":1000,"category":"TELEVISION","clue":"Current Sunday night show hosted by father & daughter","answer":"Ripley's Believe it or Not"}]},{"category":"WORLD CAPITALS","clues":[{"value":200,"category":"WORLD CAPITALS","clue":"Largest city in Africa & capital of Egypt","answer":"Cairo"},{"value":400,"category":"WORLD CAPITALS","clue":"Strong brownish-yellow paper or capital of the Philippines","answer":"Manila"},{"value":600,"category":"WORLD CAPITALS","clue":"Thought to be world's oldest existing city, it's the capital of Syria","answer":"Damascus"},{"value":800,"category":"WORLD CAPITALS","clue":"Reykjavik, the world's northernmost capital, is in this country","answer":"Iceland"},{"value":1000,"category":"WORLD CAPITALS","clue":"One of South Africa's 3 capitals","answer":"(One of) Pretoria, Cape Town, or Bloemfontein"}]},{"category":"BODY LANGUAGE","clues":[{"value":200,"category":"BODY LANGUAGE","clue":"World-wide way to say yes with your head","answer":"to nod"},{"value":400,"category":"BODY LANGUAGE","clue":"Its position was a matter of life & death to a gladiator","answer":"thumb"},{"value":600,"category":"BODY LANGUAGE","clue":"Boxers would slap each other silly if they didn't make these","answer":"fists"},{"value":800,"category":"BODY LANGUAGE","clue":"","answer":""},{"value":1000,"category":"BODY LANGUAGE","clue":"Some experts say it can be traced to infants turning their faces to reject food","answer":"saying no (shaking the head)"}]},{"category":"STARTS WITH \"P\"","clues":[{"value":200,"category":"STARTS WITH \"P\"","clue":"It's under Liberace's candelabra","answer":"piano"},{"value":400,"category":"STARTS WITH \"P\"","clue":"Italian city that disappeared because of Mt. Vesuvius","answer":"Pompeii"},{"value":600,"category":"STARTS WITH \"P\"","clue":"","answer":""},{"value":800,"category":"STARTS WITH \"P\"","clue":"","answer":""},{"value":1000,"category":"STARTS WITH \"P\"","clue":"Mormon practice outlawed by Congress in 1862","answer":"polygamy"}]},{"category":"CLASSICAL MUSIC","clues":[{"value":200,"category":"CLASSICAL MUSIC","clue":"Dudley Moore came un\"ravel\"ed when Bo put on this music","answer":"the bolero"},{"value":400,"category":"CLASSICAL MUSIC","clue":"Tchaikovsky's \"suite\" ballet; a Christmas favorite","answer":"The Nutcracker"},{"value":600,"category":"CLASSICAL MUSIC","clue":"Scarlatti wrote 600 pieces for this forerunner of the piano","answer":"harpsichord"},{"value":800,"category":"CLASSICAL MUSIC","clue":"Mozart's version of this was called \"The Marriage of Figaro\"","answer":"The Barber of Seville"},{"value":1000,"category":"CLASSICAL MUSIC","clue":"\"Bel canto\" is one way of doing it","answer":"singing"}]}],"final_jeopardy":{"category":"U.S. STATES","clue":"This state was once an independent monarchy","answer":"Hawaii"}}