{"comments":"","jeopardy":[{"category":"GALILEO","clues":[{"value":200,"category":"GALILEO","answer":"the Sun","clue":"His studies of spots on this body may have ruined his eyes; he went blind a few years before his death","daily_double?":false},{"value":400,"category":"GALILEO","answer":"Galilei","clue":"Galileo's last name","daily_double?":false},{"value":600,"category":"GALILEO","answer":"a microscope","clue":"Galileo made one of these by reversing & adjusting the lenses in one of his telescopes","daily_double?":false},{"value":800,"category":"GALILEO","answer":"Pisa","clue":"Galileo was born in this city in which legend says he performed his falling ball test","daily_double?":false},{"value":1000,"category":"GALILEO","answer":"a pendulum","clue":"Galileo suggested that the action of one of these could be used to regulate a clock","daily_double?":false}]},{"category":"FILMS OF THE '70s","clues":[{"value":200,"category":"FILMS OF THE '70s","answer":"Chinatown","clue":"Besides directing this 1974 film, Roman Polanski played a gangster who cut Jack Nicholson's nose","daily_double?":false},{"value":400,"category":"FILMS OF THE '70s","answer":"Network","clue":"Film in which Peter Finch yelled, \"I'm mad as hell and I'm not going to take it anymore!\"","daily_double?":false},{"value":600,"category":"FILMS OF THE '70s","answer":"Superman","clue":"Marlon Brando received $3 million to play Jor-El in this 1978 film","daily_double?":false},{"value":800,"category":"FILMS OF THE '70s","answer":"Woody Guthrie","clue":"David Carradine starred in \"Bound for Glory\", a 1976 biography of this folk singer","daily_double?":false},{"value":1000,"category":"FILMS OF THE '70s","answer":"Murder on the Orient Express","clue":"This Hercule Poirot mystery took place during a journey from Istanbul to Paris","daily_double?":false}]},{"category":"LANDMARKS","clues":[{"value":200,"category":"LANDMARKS","answer":"Mount Rushmore","clue":"This South Dakota landmark has been called the \"Shrine of Democracy\"","daily_double?":false},{"value":400,"category":"LANDMARKS","answer":"Bangkok","clue":"The Temple of the Emerald Buddha stands on the grounds of the Grand Palace in this Thai capital","daily_double?":false},{"value":600,"category":"LANDMARKS","answer":"the Arc de Triomphe","clue":"The inner walls of this Paris landmark bear the names of 386 of Napoleon's generals","daily_double?":true},{"value":800,"category":"LANDMARKS","answer":"the Superdome","clue":"This New Orleans arena reaches a peak height of 27 stories","daily_double?":false},{"value":1000,"category":"LANDMARKS","answer":"Budapest","clue":"St. Stephen's Basilica is a famous landmark in this European capital","daily_double?":false}]},{"category":"FEBRUARY","clues":[{"value":200,"category":"FEBRUARY","answer":"the Nile","clue":"On February 23, 1863, Captains Speke & Grant announced they had found the source of this river","daily_double?":false},{"value":400,"category":"FEBRUARY","answer":"Rushdie","clue":"On February 14, 1989, the Ayatollah Khomeini issued a famous fatwah concerning this author","daily_double?":false},{"value":600,"category":"FEBRUARY","answer":"Kellogg","clue":"In February 1906 he formed the Battle Creek Toasted Corn Flake Company","daily_double?":false},{"value":800,"category":"FEBRUARY","answer":"Powers","clue":"On February 10, 1962, the Russians released this U.S. pilot","daily_double?":false},{"value":1000,"category":"FEBRUARY","answer":"Egypt & Syria","clue":"On February 1, 1958, these 2 countries joined to form the United Arab Republic","daily_double?":false}]},{"category":"ETIQUETTE","clues":[{"value":200,"category":"ETIQUETTE","answer":"R.S.V.P","clue":"On an invitation the words \"The favour of a reply is requested\" may replace this abbreviation","daily_double?":false},{"value":400,"category":"ETIQUETTE","answer":"a tea set","clue":"A complete one of these sets includes a caddy & a strainer","daily_double?":false},{"value":600,"category":"ETIQUETTE","answer":"brandy","clue":"Serve this liquor in a glass with a short stem so you can warm it in the palm of your hand","daily_double?":false},{"value":800,"category":"ETIQUETTE","answer":"lace","clue":"This delicate openwork fabric is the traditional gift for a 13th anniversary","daily_double?":false},{"value":1000,"category":"ETIQUETTE","answer":"a saltcellar","clue":"If this tiny bowl made to hold salt has no spoon, you may use the tip of a clean knife to serve yourself","daily_double?":false}]},{"category":"AUTO MAKES & MODELS","clues":[{"value":200,"category":"AUTO MAKES & MODELS","answer":"Lincolns","clue":"Mark VIII,\nTown Car,\nContinental","daily_double?":false},{"value":400,"category":"AUTO MAKES & MODELS","answer":"Cadillacs","clue":"De Ville,\nEldorado,\nFleetwood","daily_double?":false},{"value":600,"category":"AUTO MAKES & MODELS","answer":"Jeeps","clue":"Cherokee,\nComanche,\nGrand Wagoneer","daily_double?":false},{"value":800,"category":"AUTO MAKES & MODELS","answer":"Volkswagen","clue":"Passat,\nJetta,\nGolf","daily_double?":false},{"value":1000,"category":"AUTO MAKES & MODELS","answer":"Infiniti","clue":"G20,\nM30,\nQ45","daily_double?":false}]}],"air_date":"1995-02-27","double_jeopardy":[{"category":"HISTORICAL TERMS","clues":[{"value":400,"category":"HISTORICAL TERMS","answer":"Minutemen","clue":"The name of these Colonial militiamen comes from their claim that they could be ready in 60 seconds","daily_double?":false},{"value":800,"category":"HISTORICAL TERMS","answer":"Marx","clue":"This author of \"Das Kapital\" coined the term Lumpenproletariat to describe \"social scum\"","daily_double?":false},{"value":1200,"category":"HISTORICAL TERMS","answer":"McCarthyism","clue":"This term for the anticommunist hysteria of the '40s & '50s comes from a senator's name","daily_double?":false},{"value":1600,"category":"HISTORICAL TERMS","answer":"the Levant","clue":"This term for the countries of the Eastern Mediterranean comes from the French lever, meaning \"to rise\"","daily_double?":false},{"value":2000,"category":"HISTORICAL TERMS","answer":"the Raj","clue":"This term for British rule in India comes from Hindi for \"sovereignty\"","daily_double?":false}]},{"category":"FINLAND","clues":[{"value":400,"category":"FINLAND","answer":"saunas","clue":"There are about half a million of these traditional steam baths in the country, 1 for every 10 Finns","daily_double?":false},{"value":800,"category":"FINLAND","answer":"the Arctic Circle","clue":"About 1/3 of Finland's territory lies above this geographic line equal to 66 1/2° North","daily_double?":false},{"value":1200,"category":"FINLAND","answer":"the Lutheran Church","clue":"Finland's president serves as head of this church to which 90% of the residents belong","daily_double?":false},{"value":1600,"category":"FINLAND","answer":"Swedish","clue":"This second language of Finland is the mother tongue of about 7% of the people","daily_double?":false},{"value":2000,"category":"FINLAND","answer":"(Jean) Sibelius","clue":"The monument to this monumental Finnish composer consists of hundreds of steel pipes welded together","daily_double?":false}]},{"category":"WOMEN IN MYTHOLOGY","clues":[{"value":400,"category":"WOMEN IN MYTHOLOGY","answer":"the Gorgons","clue":"These sisters had wings & claws but were more famous for their reptilian tresses","daily_double?":false},{"value":800,"category":"WOMEN IN MYTHOLOGY","answer":"the Sphinx","clue":"When Haemon couldn't answer this monster's famous riddle, she ate him","daily_double?":false},{"value":1200,"category":"WOMEN IN MYTHOLOGY","answer":"the Earth","clue":"In Greek mythology, Gaea is the personification of this planet","daily_double?":false},{"value":1600,"category":"WOMEN IN MYTHOLOGY","answer":"Electra","clue":"The name of this heroine of a Sophocles tragedy means the bright or brilliant one","daily_double?":true},{"value":2000,"category":"WOMEN IN MYTHOLOGY","answer":"Circe","clue":"This sorceress so enchanted Ulysses that some say he had 3 sons with her","daily_double?":false}]},{"category":"VICE PRESIDENTS","clues":[{"value":400,"category":"VICE PRESIDENTS","answer":"Richard Milhouse Nixon","clue":"When inaugurated at age 40 on January 20, 1953 he became the second-youngest vice president","daily_double?":false},{"value":800,"category":"VICE PRESIDENTS","answer":"Aaron Burr","clue":"This 1st vice president of Thomas Jefferson was the grandson of famous preacher Jonathan Edwards","daily_double?":true},{"value":1200,"category":"VICE PRESIDENTS","answer":"(Hubert) Humphrey","clue":"In 1939 he graduated magna cum laude from the University of Minnesota","daily_double?":false},{"value":1600,"category":"VICE PRESIDENTS","answer":"(Alben) Barkley","clue":"This running mate of Harry Truman was the 1st vice president to sit on the National Security Council","daily_double?":false},{"value":2000,"category":"VICE PRESIDENTS","answer":"(John) Tyler","clue":"In 1841 he became the 1st vice president to succeed to the presidency upon the death of a president","daily_double?":false}]},{"category":"AUTOBIOGRAPHIES","clues":[{"value":400,"category":"AUTOBIOGRAPHIES","answer":"Frank Gifford","clue":"In his memoir \"The Whole Ten Yards\", he talks about football & life with Kathie Lee","daily_double?":false},{"value":800,"category":"AUTOBIOGRAPHIES","answer":"Vladimir Nabokov","clue":"Published in 1966, \"Speak, Memory\" is an account of this \"Lolita\" author's early life","daily_double?":false},{"value":1200,"category":"AUTOBIOGRAPHIES","answer":"(Sam) Walton","clue":"This retailer told his story in a 1992 book subtitled \"Made in America\"","daily_double?":false},{"value":1600,"category":"AUTOBIOGRAPHIES","answer":"Woody Herman","clue":"This jazz clarinetist wrote about his life & career in a book called \"The Woodchopper's Ball\"","daily_double?":false},{"value":2000,"category":"AUTOBIOGRAPHIES","answer":"Malcolm X","clue":"His autobiography, written with Alex Haley, was published posthumously in 1965","daily_double?":false}]},{"category":"IT'S THE BERRIES","clues":[{"value":400,"category":"IT'S THE BERRIES","answer":"strawberry","clue":"This popular shortcake fruit is often paired with rhubarb in a pie","daily_double?":false},{"value":800,"category":"IT'S THE BERRIES","answer":"the raspberry","clue":"When picked ripe this red or black berry pulls away from its core, creating a hollow center","daily_double?":false},{"value":1200,"category":"IT'S THE BERRIES","answer":"cranberries","clue":"New England Indians made their pemmican with these bog berries","daily_double?":false},{"value":1600,"category":"IT'S THE BERRIES","answer":"gooseberries","clue":"These green berries are traditional in fool, a British dessert","daily_double?":false},{"value":2000,"category":"IT'S THE BERRIES","answer":"the loganberry","clue":"This berry was named for the California judge who discovered it in the 1880s","daily_double?":false}]}],"final_jeopardy":{"category":"THE OLD TESTAMENT","answer":"the Book of Daniel","clue":"The words \"Mene, mene, tekel, upharsin\" appear in this book"},"categories":{"jeopardy":["GALILEO","FILMS OF THE '70s","LANDMARKS","FEBRUARY","ETIQUETTE","AUTO MAKES & MODELS"],"double_jeopardy":["HISTORICAL TERMS","FINLAND","WOMEN IN MYTHOLOGY","VICE PRESIDENTS","AUTOBIOGRAPHIES","IT'S THE BERRIES"],"final_jeopardy":"THE OLD TESTAMENT"},"contestants":["Peter Kogan","Charles Orck","Dave Jordan"]}